<?xml version="1.0" encoding="utf-8" ?>
<dwsync>
<file name="bootstrap-3.3.4.css" server="C:/wamp/" local="131181140726496543" remote="131181140720000000" Dst="0" />
<file name="form.css" server="C:/wamp/" local="131180755213030827" remote="131180755210000000" Dst="0" />
<file name="display.css" server="C:/wamp/" local="131181156102834371" remote="131181156100000000" Dst="0" />
<file name="Beminder.in buy and sell books table.css" server="C:/wamp/" local="131180800645842096" remote="131180800640000000" Dst="0" />
<file name="Beminder.in buy and sell books table2.css" server="C:/wamp/" local="131176940939680234" remote="131176940930000000" Dst="0" />
<file name="Beminder.in buy and sell books nav.css" server="C:/wamp/" local="131181204018605478" remote="131181204010000000" Dst="0" />
<file name="Beminder.in Buy and sell books search_page.css" server="C:/wamp/" local="131180748593087445" remote="131180748590000000" Dst="0" />
<file name="Beminder.in buy and sell books aboutus.css" server="C:/wamp/" local="131181226172191587" remote="131181226170000000" Dst="0" />
<file name="Beminder.in buy and sell books cart.css" server="C:/wamp/" local="131181227384149810" remote="131181227380000000" Dst="0" />
<file name="Beminder.in buy and sell books menu.css" server="C:/wamp/" local="131181235020473012" remote="131181235020000000" Dst="0" />
</dwsync>